nrlee_pypi_test/__init__.py
nrlee_pypi_test/tokenization.py
nrlee_pypi_test-0.1.dist-info/METADATA
nrlee_pypi_test-0.1.dist-info/WHEEL
nrlee_pypi_test-0.1.dist-info/top_level.txt
nrlee_pypi_test-0.1.dist-info/RECORD
