Metadata-Version: 2.1
Name: nrlee-pypi-test
Version: 0.1
Summary: preprocessing for Topic Modeling
Home-page: UNKNOWN
Author: nr.lee
Author-email: nr.lee@musinsa.com
License: UNKNOWN
Platform: UNKNOWN
Classifier: Programming Language :: Python :: 2.7
Classifier: Programming Language :: Python :: 3
Classifier: Programming Language :: Python :: 3.6
